neat/__init__.py
neat/activations.py
neat/config.py
neat/organism.py
neat/population.py
neat/reporter.py
neat/reproduction.py
neat/species.py
neat/utils.py
berens_neat-0.1.2.dist-info/LICENSE
berens_neat-0.1.2.dist-info/METADATA
berens_neat-0.1.2.dist-info/WHEEL
berens_neat-0.1.2.dist-info/top_level.txt
berens_neat-0.1.2.dist-info/RECORD
