Metadata-Version: 2.1
Name: berens-neat
Version: 0.1.2
Summary: A simple implementation of NEAT in Python
Author-email: Charlie Berens <charliejb3@gmail.com>
Project-URL: Homepage, https://github.com/charlieberens/neat
Classifier: Development Status :: 4 - Beta
Classifier: Programming Language :: Python :: 3
Classifier: License :: OSI Approved :: MIT License
Classifier: Operating System :: OS Independent
Requires-Python: >=3.8
License-File: LICENSE
